{
  "project_info": {
    "project_number": "993478204470",
    "project_id": "flutter-instagram-clone-f6866",
    "storage_bucket": "flutter-instagram-clone-f6866.firebasestorage.app"
  },
  "client": [
    {
      "client_info": {
        "mobilesdk_app_id": "1:993478204470:android:d2750f66ec34b85d6a4c97",
        "android_client_info": {
          "package_name": "com.gambley1.flutter_instagram_clone.staging"
        }
      },
      "oauth_client": [
        {
          "client_id": "993478204470-f6ghm26j469f3jne40e6pi31e6hk4045.apps.googleusercontent.com",
          "client_type": 3
        }
      ],
      "api_key": [
        {
          "current_key": "AIzaSyDKlVa3d7kr48rx-QbwmRt8xWNTBc40i6s"
        }
      ],
      "services": {
        "appinvite_service": {
          "other_platform_oauth_client": [
            {
              "client_id": "993478204470-f6ghm26j469f3jne40e6pi31e6hk4045.apps.googleusercontent.com",
              "client_type": 3
            },
            {
              "client_id": "993478204470-82808unnqdlu56hruj45q239fbdmvkce.apps.googleusercontent.com",
              "client_type": 2,
              "ios_info": {
                "bundle_id": "com.gambley1.flutterInstagramClone.staging"
              }
            }
          ]
        }
      }
    }
  ],
  "configuration_version": "1"
}